slurpy/__init__.py
slurpy/coreproperties.py
slurpy/data_utils.py
slurpy/getparameters.py
slurpy/lookup.py
slurpy/plot_utils.py
slurpy/slurry.py
slurpy/lookupdata/denPREM.csv
slurpy/lookupdata/gravPREM.csv
slurpy/lookupdata/presPREM.csv
slurpy/lookupdata/radAK135.csv
slurpy/lookupdata/radPREM.csv
slurpy/lookupdata/vpAK135.csv
slurpy/lookupdata/vpPREM.csv
slurpy/scripts/parameter_search.py
slurpy/scripts/seismic.py
slurpy/scripts/sensitivity.py
nondim_slurry-0.1.dist-info/LICENSE.md
nondim_slurry-0.1.dist-info/METADATA
nondim_slurry-0.1.dist-info/WHEEL
nondim_slurry-0.1.dist-info/top_level.txt
nondim_slurry-0.1.dist-info/RECORD
