Metadata-Version: 2.1
Name: nondim-slurry
Version: 0.1
Summary: Python code that solves the 1D, steady, spherical slurry       equations outlined in Wong et al (in prep, EPSL) (see also Wong et al. 2018)
Home-page: https://github.com/jnywong/nondim-slurry
Author: Jenny Wong
Author-email: jenny.wong@univ-grenoble-alpes.fr
License: LICENSE.md
Platform: UNKNOWN
Requires-Dist: pytest
